onsale/__init__.py
onsale/sale.py
onsale-0.0.4.dist-info/LICENSE
onsale-0.0.4.dist-info/METADATA
onsale-0.0.4.dist-info/WHEEL
onsale-0.0.4.dist-info/top_level.txt
onsale-0.0.4.dist-info/RECORD
