Metadata-Version: 2.1
Name: onsale
Version: 0.0.4
Summary: Put your shop on sale
Home-page: UNKNOWN
Author: Sandesh
Author-email: <mail@sandesh.com>
License: UNKNOWN
Keywords: python,sale,discount
Platform: UNKNOWN
Classifier: Development Status :: 1 - Planning
Classifier: Intended Audience :: Developers
Classifier: Programming Language :: Python :: 3
Classifier: Operating System :: Unix
Classifier: Operating System :: MacOS :: MacOS X
Classifier: Operating System :: Microsoft :: Windows
License-File: LICENSE
